icutil_IGNchinmay/__init__.py
icutil_IGNchinmay/draw_utils.py
icutil_IGNchinmay/json_utils.py
icutil_IGNchinmay/typehint_utils.py
icutil_IGNchinmay-0.0.8.dist-info/LICENSE.txt
icutil_IGNchinmay-0.0.8.dist-info/METADATA
icutil_IGNchinmay-0.0.8.dist-info/WHEEL
icutil_IGNchinmay-0.0.8.dist-info/top_level.txt
icutil_IGNchinmay-0.0.8.dist-info/RECORD
