Metadata-Version: 2.1
Name: icutil_IGNchinmay
Version: 0.0.8
Summary: A small CV test package
Author-email: Chinmay <chinmayananda.sahu@ignitarium.com>
Project-URL: Homepage, https://github.com/IGNchinmay/PypiPublishTest
Project-URL: Issues, https://github.com/IGNchinmay/PypiPublishTest/issues
Classifier: Programming Language :: Python :: 3
Classifier: License :: OSI Approved :: MIT License
Classifier: Operating System :: OS Independent
Requires-Python: >=3.8
License-File: LICENSE.txt
Requires-Dist: docker
Requires-Dist: easyprocess
Requires-Dist: fabulous
Requires-Dist: imgaug
Requires-Dist: loguru
Requires-Dist: lsb-release-ex
Requires-Dist: matplotlib
Requires-Dist: opencv-python
Requires-Dist: pandas
Requires-Dist: Pillow
Requires-Dist: pynput
Requires-Dist: scikit-image
Requires-Dist: shapely
Requires-Dist: sympy
Requires-Dist: termcolor
